plexonNEX5Converter/__init__.py
plexonNEX5Converter/controller.py
plexonNEX5Converter/gui.py
plexonNEX5Converter/model.py
plexonNEX5Converter/bin/PL2FileReader.dll
plexonNEX5Converter/bin/PL2FileReader64.dll
plexonNEX5Converter/nex/NexFileData.py
plexonNEX5Converter/nex/NexFileHeaders.py
plexonNEX5Converter/nex/NexFileReaders.py
plexonNEX5Converter/nex/NexFileWriters.py
plexonNEX5Converter/nex/Readme.txt
plexonNEX5Converter/nex/__init__.py
plexonNEX5Converter/pypl2/__init__.py
plexonNEX5Converter/pypl2/pypl2api.py
plexonNEX5Converter/pypl2/pypl2lib.py
plexonNEX5Converter/sc/__init__.py
plexonNEX5Converter/sc/sctonex5.py
h21ak9_42f821-0.1.2.dist-info/METADATA
h21ak9_42f821-0.1.2.dist-info/WHEEL
h21ak9_42f821-0.1.2.dist-info/entry_points.txt
h21ak9_42f821-0.1.2.dist-info/top_level.txt
h21ak9_42f821-0.1.2.dist-info/RECORD
