Metadata-Version: 2.1
Name: h21ak9-42f821
Version: 0.1.2
Summary: Placeholder for description
Home-page: UNKNOWN
Author: h21ak9
Author-email: h21ak9@gmail.com
License: UNKNOWN
Platform: UNKNOWN
Requires-Dist: pyside2
Requires-Dist: phylib (==2.4.3)
Requires-Dist: numpy
Requires-Dist: debugpy
